scripts/__init__.py
scripts/heatmaps.py
src/__init__.py
src/analysis.py
src/gui.py
src/scouts.ico
src/utils.py
src/violins.py
src/default_icons/application-x-executable.svg
src/default_icons/document-save.svg
src/default_icons/edit-delete.svg
src/default_icons/folder.svg
src/default_icons/go-next.svg
src/default_icons/help-about.svg
src/default_icons/list-add.svg
src/default_icons/list-remove.svg
src/default_icons/preferences-other.svg
src/default_icons/process-stop.svg
src/default_icons/science.svg
src/default_icons/system-run.svg
src/default_icons/x-office-spreadsheet.svg
tests/__init__.py
tests/unit_tests.py
scouts-0.1.4.dist-info/LICENSE.md
scouts-0.1.4.dist-info/METADATA
scouts-0.1.4.dist-info/WHEEL
scouts-0.1.4.dist-info/entry_points.txt
scouts-0.1.4.dist-info/top_level.txt
scouts-0.1.4.dist-info/RECORD
